ec_toolkit/Cargo.lock
ec_toolkit/Cargo.toml
ec_toolkit/__init__.py
ec_toolkit/_frequency_extraction.cpython-314-darwin.so
ec_toolkit/analysis/__init__.py
ec_toolkit/analysis/thermodynamics.py
ec_toolkit/io/__init__.py
ec_toolkit/io/outcar.py
ec_toolkit/io/poscar.py
ec_toolkit/io/vasp_helpers.py
ec_toolkit/models/__init__.py
ec_toolkit/models/classes.py
ec_toolkit/models/constructor.py
ec_toolkit/src/lib.rs
ec_toolkit/visualization/__init__.py
ec_toolkit/visualization/plotting.py
ec_toolkit-0.3.2.dist-info/METADATA
ec_toolkit-0.3.2.dist-info/WHEEL
ec_toolkit-0.3.2.dist-info/licenses/LICENSE
ec_toolkit-0.3.2.dist-info/RECORD
