Metadata-Version: 2.4
Name: ec-toolkit
Version: 0.3.2
Classifier: Programming Language :: Python
Classifier: Programming Language :: Rust
Classifier: Programming Language :: Python :: Implementation :: CPython
Classifier: Programming Language :: Python :: Implementation :: PyPy
Requires-Dist: ase>=3.25.0
Requires-Dist: astropy>=7.1.0
Requires-Dist: numpy>=2.3.1
Requires-Dist: sphinx ; extra == 'docs'
Requires-Dist: sphinx-autodoc-typehints ; extra == 'docs'
Requires-Dist: sphinx-rtd-theme ; extra == 'docs'
Requires-Dist: pytest>=7.0 ; extra == 'test'
Requires-Dist: pytest-cov ; extra == 'test'
Provides-Extra: docs
Provides-Extra: test
License-File: LICENSE
Summary: Electrochemical thermodynamics toolkit for VASP workflows
Requires-Python: >=3.12
